mfw
