Metadata-Version: 1.0
Name: django-mfw
Version: 0.4.0
Summary: Django framework for mobilephone/smartphone site
Home-page: https://github.com/lambdalisue/django-mfw
Author: Alisue
Author-email: lambdalisue@hashnote.net
License: MIT
Download-URL: https://github.com/lambdalisue/django-mfw/tarball/master
Keywords: django mobile smartphone emoji device detection dynamic template
Platform: UNKNOWN
Classifier: Development Status :: 4 - Beta
Classifier: Environment :: Web Environment
Classifier: Framework :: Django
Classifier: Intended Audience :: Developers
Classifier: License :: OSI Approved :: MIT License
Classifier: Programming Language :: Python
Classifier: Topic :: Internet :: WWW/HTTP
